gammapbh/__init__.py
gammapbh/__main__.py
gammapbh/cli.py
gammapbh/blackhawk_data/1.0e+14/1.0e+14.txt
gammapbh/blackhawk_data/1.0e+14/BH_spectrum.txt
gammapbh/blackhawk_data/1.0e+14/Probabilities.txt
gammapbh/blackhawk_data/1.0e+14/final_state_radiation_prim.txt
gammapbh/blackhawk_data/1.0e+14/final_state_radiation_sec.txt
gammapbh/blackhawk_data/1.0e+14/inflight_annihilation_prim.txt
gammapbh/blackhawk_data/1.0e+14/inflight_annihilation_sec.txt
gammapbh/blackhawk_data/1.0e+14/instantaneous_primary_spectra.txt
gammapbh/blackhawk_data/1.0e+14/instantaneous_secondary_spectra.txt
gammapbh/blackhawk_data/1.0e+14/instantaneous_total_spectra.txt
gammapbh/blackhawk_data/1.0e+15/1e+15.txt
gammapbh/blackhawk_data/1.0e+15/BH_spectrum.txt
gammapbh/blackhawk_data/1.0e+15/Probabilities.txt
gammapbh/blackhawk_data/1.0e+15/final_state_radiation_prim.txt
gammapbh/blackhawk_data/1.0e+15/final_state_radiation_sec.txt
gammapbh/blackhawk_data/1.0e+15/inflight_annihilation_prim.txt
gammapbh/blackhawk_data/1.0e+15/inflight_annihilation_sec.txt
gammapbh/blackhawk_data/1.0e+15/instantaneous_primary_spectra.txt
gammapbh/blackhawk_data/1.0e+15/instantaneous_secondary_spectra.txt
gammapbh/blackhawk_data/1.0e+15/instantaneous_total_spectra.txt
gammapbh/blackhawk_data/1.0e+16/1e+16.txt
gammapbh/blackhawk_data/1.0e+16/BH_spectrum.txt
gammapbh/blackhawk_data/1.0e+16/Probabilities.txt
gammapbh/blackhawk_data/1.0e+16/final_state_radiation_prim.txt
gammapbh/blackhawk_data/1.0e+16/final_state_radiation_sec.txt
gammapbh/blackhawk_data/1.0e+16/inflight_annihilation_prim.txt
gammapbh/blackhawk_data/1.0e+16/inflight_annihilation_sec.txt
gammapbh/blackhawk_data/1.0e+16/instantaneous_primary_spectra.txt
gammapbh/blackhawk_data/1.0e+16/instantaneous_secondary_spectra.txt
gammapbh/blackhawk_data/1.0e+16/instantaneous_total_spectra.txt
gammapbh/blackhawk_data/1.0e+17/1.0e+17.txt
gammapbh/blackhawk_data/1.0e+17/BH_spectrum.txt
gammapbh/blackhawk_data/1.0e+17/Probabilities.txt
gammapbh-1.1.3.dist-info/licenses/LICENSE.md
gammapbh-1.1.3.dist-info/METADATA
gammapbh-1.1.3.dist-info/WHEEL
gammapbh-1.1.3.dist-info/entry_points.txt
gammapbh-1.1.3.dist-info/top_level.txt
gammapbh-1.1.3.dist-info/RECORD
