Metadata-Version: 2.4
Name: gammapbh
Version: 1.1.3
Summary: GammaPBHPlotter: simulate and visualize Hawking gamma-ray spectra from PBHs
Author-email: John Carlini <jcarlini@oakland.edu>, Ilias Cholis <cholis@oakland.edu>
Project-URL: Homepage, https://github.com/jcarlini-dot/GammaPBHPlotter
Project-URL: Repository, https://github.com/jcarlini-dot/GammaPBHPlotter
Project-URL: Bug Tracker, https://github.com/jcarlini-dot/GammaPBHPlotter/issues
Project-URL: PyPI, https://pypi.org/project/gammapbh/
Keywords: primordial black holes,hawking radiation,gamma rays,astrophysics
Classifier: Programming Language :: Python :: 3
Classifier: Programming Language :: Python :: 3 :: Only
Classifier: Operating System :: OS Independent
Classifier: Intended Audience :: Science/Research
Classifier: Topic :: Scientific/Engineering :: Physics
Classifier: License :: OSI Approved :: GNU General Public License v3 (GPLv3)
Requires-Python: >=3.9
License-File: LICENSE.md
Requires-Dist: numpy>=1.17
Requires-Dist: scipy>=1.7
Requires-Dist: matplotlib>=3.3
Requires-Dist: tqdm>=4.60
Requires-Dist: colorama>=0.4
Dynamic: license-file
